br_registrations/__init__.py
br_registrations/validateCNPJ.py
br_registrations/validateCPF.py
br_registrations/version.py
br_registrations-0.0.1.0.dist-info/LICENSE.txt
br_registrations-0.0.1.0.dist-info/METADATA
br_registrations-0.0.1.0.dist-info/WHEEL
br_registrations-0.0.1.0.dist-info/top_level.txt
br_registrations-0.0.1.0.dist-info/RECORD
