Metadata-Version: 2.1
Name: br-registrations
Version: 0.0.1.0
Summary: A simple Python library containing functions that check Brazilian documents values
Home-page: https://pypi.org/project/br-registrations/
Author: Sliatecinos
Author-email: sliatecinos@hotmail.com
License: MIT
Project-URL: Documentation, https://br-registrations.readthedocs.io/pt_BR/latest/
Project-URL: Source, https://github.com/sliatecinos/br_registrations
Keywords: cpf,cnpj,br,brazil,brasil,validate
Platform: UNKNOWN
Classifier: Development Status :: 3 - Alpha
Classifier: Intended Audience :: Education
Classifier: Operating System :: Microsoft :: Windows :: Windows 10
Classifier: License :: OSI Approved :: MIT License
Classifier: Programming Language :: Python :: 3
License-File: LICENSE.txt
